LICENSE
MANIFEST.in
README.md
README.rst
setup.py
unicampauth/__init__.py
unicampauth/admin.py
unicampauth/apps.py
unicampauth/authenticators.py
unicampauth/conf.py
unicampauth/models.py
unicampauth/settings.py
unicampauth/tests.py
unicampauth/urls.py
unicampauth/validators.py
unicampauth/views.py
unicampauth.egg-info/PKG-INFO
unicampauth.egg-info/SOURCES.txt
unicampauth.egg-info/dependency_links.txt
unicampauth.egg-info/requires.txt
unicampauth.egg-info/top_level.txt
unicampauth/migrations/0001_initial.py
unicampauth/migrations/__init__.py